{
  "slot": [
    {
      "category": 0.0,
      "points": [
        [
          218.52665421345162,
          46.15333636093625
        ],
        [
          321.77998641154835,
          124.66000287246219
        ]
      ],
      "angle1": 2.2208762168884277,
      "angle2": 2.2208762168884277,
      "ignore": 0.0,
      "vacant": 0.0
    },
    {
      "category": 0.0,
      "points": [
        [
          321.780006553745,
          124.65999428238297
        ],
        [
          425.88668045797374,
          205.72666343246078
        ]
      ],
      "angle1": 2.2324066162109375,
      "angle2": 2.2324066162109375,
      "ignore": 0.0,
      "vacant": 0.0
    }
  ]
}