{
  "slot": [
    {
      "category": 0.0,
      "points": [
        [
          350.7933385151098,
          176.7133323861904
        ],
        [
          335.4333460552027,
          309.83332899076277
        ]
      ],
      "angle1": -3.0267159938812256,
      "angle2": -3.0267159938812256,
      "ignore": 0.0,
      "vacant": 0.0
    },
    {
      "category": 0.0,
      "points": [
        [
          335.43332372982525,
          309.83333706567737
        ],
        [
          323.486659180331,
          446.3666751413539
        ]
      ],
      "angle1": -3.0543148517608643,
      "angle2": -3.0543148517608643,
      "ignore": 0.0,
      "vacant": 0.0
    }
  ]
}