{
  "slot": [
    {
      "category": 0.0,
      "points": [
        [
          321.7800005911892,
          115.27332822939789
        ],
        [
          323.48666200646704,
          252.65999086239898
        ]
      ],
      "angle1": 3.1291708946228027,
      "angle2": 3.1291708946228027,
      "ignore": 0.0,
      "vacant": 1.0
    },
    {
      "category": 0.0,
      "points": [
        [
          323.486661508197,
          252.66000036140935
        ],
        [
          322.6333336089905,
          384.0733370409344
        ]
      ],
      "angle1": -3.135099172592163,
      "angle2": -3.135099172592163,
      "ignore": 0.0,
      "vacant": 0.0
    }
  ]
}