{
  "slot": [
    {
      "category": 0.0,
      "points": [
        [
          441.24666798627925,
          180.1266759472722
        ],
        [
          446.366674298877,
          318.36667122069656
        ]
      ],
      "angle1": 3.1045725345611572,
      "angle2": 3.1045725345611572,
      "ignore": 0.0,
      "vacant": 0.0
    },
    {
      "category": 0.0,
      "points": [
        [
          150.2599967038637,
          340.55332508035076
        ],
        [
          140.87333459496443,
          195.486652946993
        ]
      ],
      "angle1": -0.06461580097675323,
      "angle2": -0.06461580097675323,
      "ignore": 0.0,
      "vacant": 1.0
    }
  ]
}