{
  "slot": [
    {
      "category": 0.0,
      "points": [
        [
          124.66000109111533,
          466.84665581933126
        ],
        [
          116.12666577900185,
          322.63332464941874
        ]
      ],
      "angle1": -0.05910268425941467,
      "angle2": -0.05910268425941467,
      "ignore": 0.0,
      "vacant": 1.0
    },
    {
      "category": 0.0,
      "points": [
        [
          116.12666825142311,
          322.6333370055631
        ],
        [
          108.44666548881126,
          184.39333535771817
        ]
      ],
      "angle1": -0.055498506873846054,
      "angle2": -0.055498506873846054,
      "ignore": 0.0,
      "vacant": 1.0
    }
  ]
}