{
  "slot": [
    {
      "category": 0.0,
      "points": [
        [
          118.68666612760052,
          370.4200105766242
        ],
        [
          146.84665906771198,
          250.10000895462582
        ]
      ],
      "angle1": 0.2299044281244278,
      "angle2": 0.2299044281244278,
      "ignore": 0.0,
      "vacant": 1.0
    },
    {
      "category": 0.0,
      "points": [
        [
          158.7933357593888,
          191.21999841245002
        ],
        [
          188.66000286365806,
          70.89999670473749
        ]
      ],
      "angle1": 0.24330921471118927,
      "angle2": 0.24330921471118927,
      "ignore": 0.0,
      "vacant": 1.0
    }
  ]
}