{
  "slot": [
    {
      "category": 0.0,
      "points": [
        [
          130.6333334672665,
          423.3266663251376
        ],
        [
          122.95333645460848,
          275.70000603814367
        ]
      ],
      "angle1": -0.051976267248392105,
      "angle2": -0.051976267248392105,
      "ignore": 0.0,
      "vacant": 0.0
    },
    {
      "category": 0.0,
      "points": [
        [
          119.54000080518723,
          203.1666678206028
        ],
        [
          114.42000590867995,
          58.09999477705344
        ]
      ],
      "angle1": -0.03527947515249252,
      "angle2": -0.03527947515249252,
      "ignore": 0.0,
      "vacant": 0.0
    }
  ]
}