{
  "slot": [
    {
      "category": 0.0,
      "points": [
        [
          78.58000112223608,
          378.9533391577668
        ],
        [
          62.36666940999047,
          252.66000312738944
        ]
      ],
      "angle1": -0.1276800036430359,
      "angle2": -0.1276800036430359,
      "ignore": 0.0,
      "vacant": 0.0
    },
    {
      "category": 0.0,
      "points": [
        [
          62.36667130576314,
          252.65999950260564
        ],
        [
          47.006665486229046,
          132.34000049739436
        ]
      ],
      "angle1": -0.12697279453277588,
      "angle2": -0.12697279453277588,
      "ignore": 0.0,
      "vacant": 0.0
    },
    {
      "category": 0.0,
      "points": [
        [
          423.32665416301256,
          78.58000463468052
        ],
        [
          437.8333189815187,
          204.02000146883512
        ]
      ],
      "angle1": 3.0264577865600586,
      "angle2": 3.0264577865600586,
      "ignore": 0.0,
      "vacant": 0.0
    },
    {
      "category": 0.0,
      "points": [
        [
          437.83333486816946,
          204.01999136976792
        ],
        [
          453.1933374951118,
          329.4599890989821
        ]
      ],
      "angle1": 3.0197501182556152,
      "angle2": 3.0197501182556152,
      "ignore": 0.0,
      "vacant": 0.0
    }
  ]
}