{
  "slot": [
    {
      "category": 0.0,
      "points": [
        [
          425.8866556036278,
          257.779992461912
        ],
        [
          300.44665738465346,
          277.4066530459005
        ]
      ],
      "angle1": -1.7260005474090576,
      "angle2": -1.7260005474090576,
      "ignore": 0.0,
      "vacant": 0.0
    },
    {
      "category": 0.0,
      "points": [
        [
          300.4466700489358,
          277.4066693910826
        ],
        [
          172.44667101551732,
          296.1800005307924
        ]
      ],
      "angle1": -1.7164247035980225,
      "angle2": -1.7164247035980225,
      "ignore": 0.0,
      "vacant": 0.0
    },
    {
      "category": 0.0,
      "points": [
        [
          172.44665955185056,
          296.18001311656104
        ],
        [
          43.593333734282254,
          317.51334625843896
        ]
      ],
      "angle1": -1.7348709106445312,
      "angle2": -1.7348709106445312,
      "ignore": 0.0,
      "vacant": 1.0
    }
  ]
}