{
  "slot": [
    {
      "category": 0.0,
      "points": [
        [
          425.88665704874023,
          257.7799883039934
        ],
        [
          301.29998845907227,
          277.4066572038191
        ]
      ],
      "angle1": -1.7270464897155762,
      "angle2": -1.7270464897155762,
      "ignore": 0.0,
      "vacant": 0.0
    },
    {
      "category": 0.0,
      "points": [
        [
          301.3000040077575,
          277.406673902286
        ],
        [
          172.4466695762269,
          296.179996019589
        ]
      ],
      "angle1": -1.7154737710952759,
      "angle2": -1.7154737710952759,
      "ignore": 0.0,
      "vacant": 0.0
    },
    {
      "category": 0.0,
      "points": [
        [
          172.44666006905962,
          296.1800059232031
        ],
        [
          42.740000697541944,
          317.5133534517969
        ]
      ],
      "angle1": -1.733810544013977,
      "angle2": -1.733810544013977,
      "ignore": 0.0,
      "vacant": 1.0
    }
  ]
}