{
  "slot": [
    {
      "category": 0.0,
      "points": [
        [
          416.5000171601824,
          262.9000157636379
        ],
        [
          323.4866771757551,
          349.0866785722996
        ]
      ],
      "angle1": -2.318117618560791,
      "angle2": -2.318117618560791,
      "ignore": 0.0,
      "vacant": 0.0
    },
    {
      "category": 0.0,
      "points": [
        [
          323.48667807543677,
          349.086663295849
        ],
        [
          230.4733438972195,
          437.83331961430724
        ]
      ],
      "angle1": -2.3327245712280273,
      "angle2": -2.3327245712280273,
      "ignore": 0.0,
      "vacant": 0.0
    }
  ]
}