{
  "slot": [
    {
      "category": 0.0,
      "points": [
        [
          331.1666538469716,
          411.38000206712877
        ],
        [
          211.69998433662215,
          476.2333402180275
        ]
      ],
      "angle1": -2.06813907623291,
      "angle2": -2.06813907623291,
      "ignore": 0.0,
      "vacant": 0.0
    },
    {
      "category": 0.0,
      "points": [
        [
          449.77999071862007,
          347.38000313769106
        ],
        [
          331.16666455481743,
          411.38000662793394
        ]
      ],
      "angle1": -2.0655953884124756,
      "angle2": -2.0655953884124756,
      "ignore": 0.0,
      "vacant": 1.0
    }
  ]
}