{
  "slot": [
    {
      "category": 0.0,
      "points": [
        [
          174.15333675524812,
          254.36666540279347
        ],
        [
          44.44666934826749,
          250.95334192142528
        ]
      ],
      "angle1": -1.54448664188385,
      "angle2": -1.54448664188385,
      "ignore": 0.0,
      "vacant": 0.0
    },
    {
      "category": 0.0,
      "points": [
        [
          311.53999939976495,
          260.3400053118626
        ],
        [
          174.1533294576569,
          254.3666597271999
        ]
      ],
      "angle1": -1.5273454189300537,
      "angle2": -1.5273454189300537,
      "ignore": 0.0,
      "vacant": 0.0
    },
    {
      "category": 0.0,
      "points": [
        [
          444.66000737261675,
          266.31332446925876
        ],
        [
          311.5400048344145,
          260.33999584324124
        ]
      ],
      "angle1": -1.5259546041488647,
      "angle2": -1.5259546041488647,
      "ignore": 0.0,
      "vacant": 1.0
    }
  ]
}