{
  "slot": [
    {
      "category": 0.0,
      "points": [
        [
          192.07333797249393,
          141.72666519785525
        ],
        [
          314.10000187125604,
          184.39332991933225
        ]
      ],
      "angle1": 1.9071595668792725,
      "angle2": 1.9071595668792725,
      "ignore": 0.0,
      "vacant": 0.0
    },
    {
      "category": 0.0,
      "points": [
        [
          314.10000865259195,
          184.39333672976255
        ],
        [
          433.5666783591268,
          224.50000433469057
        ]
      ],
      "angle1": 1.8946882486343384,
      "angle2": 1.8946882486343384,
      "ignore": 0.0,
      "vacant": 0.0
    }
  ]
}