{
  "slot": [
    {
      "category": 0.0,
      "points": [
        [
          134.0466633853483,
          437.83332456730716
        ],
        [
          133.1933268490267,
          292.76665101863034
        ]
      ],
      "angle1": -0.0058822850696742535,
      "angle2": -0.0058822850696742535,
      "ignore": 0.0,
      "vacant": 1.0
    },
    {
      "category": 0.0,
      "points": [
        [
          133.19333189740345,
          292.7666702270507
        ],
        [
          133.1933258174403,
          153.67333221435553
        ]
      ],
      "angle1": 0.0,
      "angle2": 0.0,
      "ignore": 0.0,
      "vacant": 1.0
    }
  ]
}