{
  "slot": [
    {
      "category": 0.0,
      "points": [
        [
          242.41998699997225,
          35.91333579535551
        ],
        [
          364.4466511836215,
          82.84666634087496
        ]
      ],
      "angle1": 1.9379701614379883,
      "angle2": 1.9379701614379883,
      "ignore": 0.0,
      "vacant": 0.0
    },
    {
      "category": 0.0,
      "points": [
        [
          426.7400130355893,
          419.0599915280717
        ],
        [
          311.5400162612857,
          375.5399840578658
        ]
      ],
      "angle1": -1.209592580795288,
      "angle2": -1.209592580795288,
      "ignore": 0.0,
      "vacant": 0.0
    },
    {
      "category": 0.0,
      "points": [
        [
          311.540001825001,
          375.5399995431837
        ],
        [
          195.48667053828024,
          327.7533354177538
        ]
      ],
      "angle1": -1.1801892518997192,
      "angle2": -1.1801892518997192,
      "ignore": 0.0,
      "vacant": 0.0
    },
    {
      "category": 0.0,
      "points": [
        [
          195.4866721047336,
          327.7533228107472
        ],
        [
          79.43334132300076,
          277.40665033378406
        ]
      ],
      "angle1": -1.1614758968353271,
      "angle2": -1.1614758968353271,
      "ignore": 0.0,
      "vacant": 0.0
    }
  ]
}