{
  "slot": [
    {
      "category": 0.0,
      "points": [
        [
          407.96667683818623,
          52.98000293077552
        ],
        [
          404.55334269306377,
          169.88666577039635
        ]
      ],
      "angle1": -3.1124038696289062,
      "angle2": -3.1124038696289062,
      "ignore": 0.0,
      "vacant": 1.0
    },
    {
      "category": 0.0,
      "points": [
        [
          404.5533462400407,
          169.88666163023498
        ],
        [
          400.28668061542805,
          288.49999608460877
        ]
      ],
      "angle1": -3.1056368350982666,
      "angle2": -3.1056368350982666,
      "ignore": 0.0,
      "vacant": 1.0
    },
    {
      "category": 0.0,
      "points": [
        [
          400.28665364482686,
          288.50000720323646
        ],
        [
          396.8733194997044,
          405.4066700428573
        ]
      ],
      "angle1": -3.1124038696289062,
      "angle2": -3.1124038696289062,
      "ignore": 0.0,
      "vacant": 0.0
    }
  ]
}