{
  "slot": [
    {
      "category": 0.0,
      "points": [
        [
          397.7266536072357,
          181.83332988669665
        ],
        [
          396.8733219787018,
          307.2733290488502
        ]
      ],
      "angle1": -3.1347899436950684,
      "angle2": -3.1347899436950684,
      "ignore": 0.0,
      "vacant": 1.0
    },
    {
      "category": 0.0,
      "points": [
        [
          396.8733242188309,
          307.27334976196295
        ],
        [
          396.8733188475754,
          430.1533470153808
        ]
      ],
      "angle1": 3.1415927410125732,
      "angle2": 3.1415927410125732,
      "ignore": 0.0,
      "vacant": 1.0
    }
  ]
}