{
  "slot": [
    {
      "category": 0.0,
      "points": [
        [
          125.51333235784303,
          384.07333883113665
        ],
        [
          122.09999466852416,
          244.98000589542585
        ]
      ],
      "angle1": -0.024534953758120537,
      "angle2": -0.024534953758120537,
      "ignore": 0.0,
      "vacant": 0.0
    },
    {
      "category": 0.0,
      "points": [
        [
          122.09999966338397,
          244.97999746411352
        ],
        [
          119.53999972626447,
          111.00666635424584
        ]
      ],
      "angle1": -0.019105955958366394,
      "angle2": -0.019105955958366394,
      "ignore": 0.0,
      "vacant": 1.0
    }
  ]
}